<?xml version="1.0" encoding="utf-8"?>
<abapGit version="v1.0.0" serializer="LCL_OBJECT_WEBI" serializer_version="v1.0.0">
 <asx:abap xmlns:asx="http://www.sap.com/abapxml" version="1.0">
  <asx:values>
   <WEBI>
    <VEPTEXT>SERVICE DEFINITION FOR GOODS RECEIPT</VEPTEXT>
    <PVEPHEADER>
     <VEPHEADER>
      <VEPNAME>ZSD_VEN_GOODSRECEIPT_YM</VEPNAME>
      <VERSION>A</VERSION>
      <VEPNAMEEXT>ZSD_VEN_GOODSRECEIPT_YM</VEPNAMEEXT>
      <DEFAULT_MAPPING>X</DEFAULT_MAPPING>
     </VEPHEADER>
    </PVEPHEADER>
    <PVEPFUNCTION>
     <VEPFUNCTION>
      <VEPNAME>ZSD_VEN_GOODSRECEIPT_YM</VEPNAME>
      <VERSION>A</VERSION>
      <FUNCTION>ZFM_VEN_GOODSRECEIPT_YM</FUNCTION>
      <MAPPEDNAME>ZfmVenGoodsreceiptYm</MAPPEDNAME>
      <IS_EXPOSED>X</IS_EXPOSED>
     </VEPFUNCTION>
    </PVEPFUNCTION>
    <PVEPPARAMETER>
     <VEPPARAMETER>
      <VEPNAME>ZSD_VEN_GOODSRECEIPT_YM</VEPNAME>
      <VERSION>A</VERSION>
      <FUNCTION>ZFM_VEN_GOODSRECEIPT_YM</FUNCTION>
      <VEPPARAM>EV_VEN_GR</VEPPARAM>
      <VEPPARAMTYPE>O</VEPPARAMTYPE>
      <MAPPEDNAME>EvVenGr</MAPPEDNAME>
      <IS_EXPOSED>X</IS_EXPOSED>
      <IS_INITIAL>X</IS_INITIAL>
      <TYPENAME>ZttVenReceiptYm</TYPENAME>
     </VEPPARAMETER>
     <VEPPARAMETER>
      <VEPNAME>ZSD_VEN_GOODSRECEIPT_YM</VEPNAME>
      <VERSION>A</VERSION>
      <FUNCTION>ZFM_VEN_GOODSRECEIPT_YM</FUNCTION>
      <VEPPARAM>IV_DOC</VEPPARAM>
      <VEPPARAMTYPE>I</VEPPARAMTYPE>
      <MAPPEDNAME>IvDoc</MAPPEDNAME>
      <IS_EXPOSED>X</IS_EXPOSED>
      <IS_INITIAL>X</IS_INITIAL>
      <TYPENAME>LIFNR</TYPENAME>
     </VEPPARAMETER>
    </PVEPPARAMETER>
    <PVEPTYPE>
     <VEPTYPE>
      <VEPNAME>ZSD_VEN_GOODSRECEIPT_YM</VEPNAME>
      <VERSION>A</VERSION>
      <TYPENAME>BLART</TYPENAME>
      <TYPE>E</TYPE>
     </VEPTYPE>
     <VEPTYPE>
      <VEPNAME>ZSD_VEN_GOODSRECEIPT_YM</VEPNAME>
      <VERSION>A</VERSION>
      <TYPENAME>BLDAT</TYPENAME>
      <TYPE>E</TYPE>
     </VEPTYPE>
     <VEPTYPE>
      <VEPNAME>ZSD_VEN_GOODSRECEIPT_YM</VEPNAME>
      <VERSION>A</VERSION>
      <TYPENAME>BSTNR</TYPENAME>
      <TYPE>E</TYPE>
     </VEPTYPE>
     <VEPTYPE>
      <VEPNAME>ZSD_VEN_GOODSRECEIPT_YM</VEPNAME>
      <VERSION>A</VERSION>
      <TYPENAME>BUDAT</TYPENAME>
      <TYPE>E</TYPE>
     </VEPTYPE>
     <VEPTYPE>
      <VEPNAME>ZSD_VEN_GOODSRECEIPT_YM</VEPNAME>
      <VERSION>A</VERSION>
      <TYPENAME>BWART</TYPENAME>
      <TYPE>E</TYPE>
     </VEPTYPE>
     <VEPTYPE>
      <VEPNAME>ZSD_VEN_GOODSRECEIPT_YM</VEPNAME>
      <VERSION>A</VERSION>
      <TYPENAME>EBELP</TYPENAME>
      <TYPE>E</TYPE>
     </VEPTYPE>
     <VEPTYPE>
      <VEPNAME>ZSD_VEN_GOODSRECEIPT_YM</VEPNAME>
      <VERSION>A</VERSION>
      <TYPENAME>ELIFN</TYPENAME>
      <TYPE>E</TYPE>
     </VEPTYPE>
     <VEPTYPE>
      <VEPNAME>ZSD_VEN_GOODSRECEIPT_YM</VEPNAME>
      <VERSION>A</VERSION>
      <TYPENAME>LGORT_D</TYPENAME>
      <TYPE>E</TYPE>
     </VEPTYPE>
     <VEPTYPE>
      <VEPNAME>ZSD_VEN_GOODSRECEIPT_YM</VEPNAME>
      <VERSION>A</VERSION>
      <TYPENAME>LIFNR</TYPENAME>
      <TYPE>E</TYPE>
     </VEPTYPE>
     <VEPTYPE>
      <VEPNAME>ZSD_VEN_GOODSRECEIPT_YM</VEPNAME>
      <VERSION>A</VERSION>
      <TYPENAME>MATNR</TYPENAME>
      <TYPE>E</TYPE>
     </VEPTYPE>
     <VEPTYPE>
      <VEPNAME>ZSD_VEN_GOODSRECEIPT_YM</VEPNAME>
      <VERSION>A</VERSION>
      <TYPENAME>MBLNR</TYPENAME>
      <TYPE>E</TYPE>
     </VEPTYPE>
     <VEPTYPE>
      <VEPNAME>ZSD_VEN_GOODSRECEIPT_YM</VEPNAME>
      <VERSION>A</VERSION>
      <TYPENAME>MBLPO</TYPENAME>
      <TYPE>E</TYPE>
     </VEPTYPE>
     <VEPTYPE>
      <VEPNAME>ZSD_VEN_GOODSRECEIPT_YM</VEPNAME>
      <VERSION>A</VERSION>
      <TYPENAME>MEINS</TYPENAME>
      <TYPE>E</TYPE>
     </VEPTYPE>
     <VEPTYPE>
      <VEPNAME>ZSD_VEN_GOODSRECEIPT_YM</VEPNAME>
      <VERSION>A</VERSION>
      <TYPENAME>MENGE_D</TYPENAME>
      <TYPE>E</TYPE>
     </VEPTYPE>
     <VEPTYPE>
      <VEPNAME>ZSD_VEN_GOODSRECEIPT_YM</VEPNAME>
      <VERSION>A</VERSION>
      <TYPENAME>MJAHR</TYPENAME>
      <TYPE>E</TYPE>
     </VEPTYPE>
     <VEPTYPE>
      <VEPNAME>ZSD_VEN_GOODSRECEIPT_YM</VEPNAME>
      <VERSION>A</VERSION>
      <TYPENAME>USNAM</TYPENAME>
      <TYPE>E</TYPE>
     </VEPTYPE>
     <VEPTYPE>
      <VEPNAME>ZSD_VEN_GOODSRECEIPT_YM</VEPNAME>
      <VERSION>A</VERSION>
      <TYPENAME>WERKS_D</TYPENAME>
      <TYPE>E</TYPE>
     </VEPTYPE>
     <VEPTYPE>
      <VEPNAME>ZSD_VEN_GOODSRECEIPT_YM</VEPNAME>
      <VERSION>A</VERSION>
      <TYPENAME>ZST_VEN_RECEIPT_YM</TYPENAME>
      <TYPE>S</TYPE>
     </VEPTYPE>
     <VEPTYPE>
      <VEPNAME>ZSD_VEN_GOODSRECEIPT_YM</VEPNAME>
      <VERSION>A</VERSION>
      <TYPENAME>ZTT_VEN_RECEIPT_YM</TYPENAME>
      <TYPE>T</TYPE>
     </VEPTYPE>
     <VEPTYPE>
      <VEPNAME>ZSD_VEN_GOODSRECEIPT_YM</VEPNAME>
      <VERSION>A</VERSION>
      <TYPENAME>ZstVenReceiptYm</TYPENAME>
      <ORGINAL>ZST_VEN_RECEIPT_YM</ORGINAL>
      <TYPE>S</TYPE>
     </VEPTYPE>
     <VEPTYPE>
      <VEPNAME>ZSD_VEN_GOODSRECEIPT_YM</VEPNAME>
      <VERSION>A</VERSION>
      <TYPENAME>ZttVenReceiptYm</TYPENAME>
      <ORGINAL>ZTT_VEN_RECEIPT_YM</ORGINAL>
      <TYPE>T</TYPE>
     </VEPTYPE>
    </PVEPTYPE>
    <PVEPELEMTYPE>
     <VEPELEMTYPE>
      <VEPNAME>ZSD_VEN_GOODSRECEIPT_YM</VEPNAME>
      <VERSION>A</VERSION>
      <TYPENAME>BLART</TYPENAME>
      <KIND>DTEL</KIND>
      <BUILD_IN_TYPE>CHAR</BUILD_IN_TYPE>
      <LENGTH>2</LENGTH>
      <ABAPTYPE>C</ABAPTYPE>
     </VEPELEMTYPE>
     <VEPELEMTYPE>
      <VEPNAME>ZSD_VEN_GOODSRECEIPT_YM</VEPNAME>
      <VERSION>A</VERSION>
      <TYPENAME>BLDAT</TYPENAME>
      <KIND>DTEL</KIND>
      <BUILD_IN_TYPE>DATS</BUILD_IN_TYPE>
      <LENGTH>8</LENGTH>
      <ABAPTYPE>D</ABAPTYPE>
     </VEPELEMTYPE>
     <VEPELEMTYPE>
      <VEPNAME>ZSD_VEN_GOODSRECEIPT_YM</VEPNAME>
      <VERSION>A</VERSION>
      <TYPENAME>BSTNR</TYPENAME>
      <KIND>DTEL</KIND>
      <BUILD_IN_TYPE>CHAR</BUILD_IN_TYPE>
      <LENGTH>10</LENGTH>
      <ABAPTYPE>C</ABAPTYPE>
     </VEPELEMTYPE>
     <VEPELEMTYPE>
      <VEPNAME>ZSD_VEN_GOODSRECEIPT_YM</VEPNAME>
      <VERSION>A</VERSION>
      <TYPENAME>BUDAT</TYPENAME>
      <KIND>DTEL</KIND>
      <BUILD_IN_TYPE>DATS</BUILD_IN_TYPE>
      <LENGTH>8</LENGTH>
      <ABAPTYPE>D</ABAPTYPE>
     </VEPELEMTYPE>
     <VEPELEMTYPE>
      <VEPNAME>ZSD_VEN_GOODSRECEIPT_YM</VEPNAME>
      <VERSION>A</VERSION>
      <TYPENAME>BWART</TYPENAME>
      <KIND>DTEL</KIND>
      <BUILD_IN_TYPE>CHAR</BUILD_IN_TYPE>
      <LENGTH>3</LENGTH>
      <ABAPTYPE>C</ABAPTYPE>
     </VEPELEMTYPE>
     <VEPELEMTYPE>
      <VEPNAME>ZSD_VEN_GOODSRECEIPT_YM</VEPNAME>
      <VERSION>A</VERSION>
      <TYPENAME>EBELP</TYPENAME>
      <KIND>DTEL</KIND>
      <BUILD_IN_TYPE>NUMC</BUILD_IN_TYPE>
      <LENGTH>5</LENGTH>
      <ABAPTYPE>N</ABAPTYPE>
     </VEPELEMTYPE>
     <VEPELEMTYPE>
      <VEPNAME>ZSD_VEN_GOODSRECEIPT_YM</VEPNAME>
      <VERSION>A</VERSION>
      <TYPENAME>ELIFN</TYPENAME>
      <KIND>DTEL</KIND>
      <BUILD_IN_TYPE>CHAR</BUILD_IN_TYPE>
      <LENGTH>10</LENGTH>
      <ABAPTYPE>C</ABAPTYPE>
     </VEPELEMTYPE>
     <VEPELEMTYPE>
      <VEPNAME>ZSD_VEN_GOODSRECEIPT_YM</VEPNAME>
      <VERSION>A</VERSION>
      <TYPENAME>LGORT_D</TYPENAME>
      <KIND>DTEL</KIND>
      <BUILD_IN_TYPE>CHAR</BUILD_IN_TYPE>
      <LENGTH>4</LENGTH>
      <ABAPTYPE>C</ABAPTYPE>
     </VEPELEMTYPE>
     <VEPELEMTYPE>
      <VEPNAME>ZSD_VEN_GOODSRECEIPT_YM</VEPNAME>
      <VERSION>A</VERSION>
      <TYPENAME>LIFNR</TYPENAME>
      <KIND>DTEL</KIND>
      <BUILD_IN_TYPE>CHAR</BUILD_IN_TYPE>
      <LENGTH>10</LENGTH>
      <ABAPTYPE>C</ABAPTYPE>
     </VEPELEMTYPE>
     <VEPELEMTYPE>
      <VEPNAME>ZSD_VEN_GOODSRECEIPT_YM</VEPNAME>
      <VERSION>A</VERSION>
      <TYPENAME>MATNR</TYPENAME>
      <KIND>DTEL</KIND>
      <BUILD_IN_TYPE>CHAR</BUILD_IN_TYPE>
      <LENGTH>40</LENGTH>
      <ABAPTYPE>C</ABAPTYPE>
     </VEPELEMTYPE>
     <VEPELEMTYPE>
      <VEPNAME>ZSD_VEN_GOODSRECEIPT_YM</VEPNAME>
      <VERSION>A</VERSION>
      <TYPENAME>MBLNR</TYPENAME>
      <KIND>DTEL</KIND>
      <BUILD_IN_TYPE>CHAR</BUILD_IN_TYPE>
      <LENGTH>10</LENGTH>
      <ABAPTYPE>C</ABAPTYPE>
     </VEPELEMTYPE>
     <VEPELEMTYPE>
      <VEPNAME>ZSD_VEN_GOODSRECEIPT_YM</VEPNAME>
      <VERSION>A</VERSION>
      <TYPENAME>MBLPO</TYPENAME>
      <KIND>DTEL</KIND>
      <BUILD_IN_TYPE>NUMC</BUILD_IN_TYPE>
      <LENGTH>4</LENGTH>
      <ABAPTYPE>N</ABAPTYPE>
     </VEPELEMTYPE>
     <VEPELEMTYPE>
      <VEPNAME>ZSD_VEN_GOODSRECEIPT_YM</VEPNAME>
      <VERSION>A</VERSION>
      <TYPENAME>MEINS</TYPENAME>
      <KIND>DTEL</KIND>
      <BUILD_IN_TYPE>UNIT</BUILD_IN_TYPE>
      <LENGTH>3</LENGTH>
      <ABAPTYPE>C</ABAPTYPE>
     </VEPELEMTYPE>
     <VEPELEMTYPE>
      <VEPNAME>ZSD_VEN_GOODSRECEIPT_YM</VEPNAME>
      <VERSION>A</VERSION>
      <TYPENAME>MENGE_D</TYPENAME>
      <KIND>DTEL</KIND>
      <BUILD_IN_TYPE>QUAN</BUILD_IN_TYPE>
      <LENGTH>13</LENGTH>
      <DECIMALS>3</DECIMALS>
      <ABAPTYPE>P</ABAPTYPE>
     </VEPELEMTYPE>
     <VEPELEMTYPE>
      <VEPNAME>ZSD_VEN_GOODSRECEIPT_YM</VEPNAME>
      <VERSION>A</VERSION>
      <TYPENAME>MJAHR</TYPENAME>
      <KIND>DTEL</KIND>
      <BUILD_IN_TYPE>NUMC</BUILD_IN_TYPE>
      <LENGTH>4</LENGTH>
      <ABAPTYPE>N</ABAPTYPE>
     </VEPELEMTYPE>
     <VEPELEMTYPE>
      <VEPNAME>ZSD_VEN_GOODSRECEIPT_YM</VEPNAME>
      <VERSION>A</VERSION>
      <TYPENAME>USNAM</TYPENAME>
      <KIND>DTEL</KIND>
      <BUILD_IN_TYPE>CHAR</BUILD_IN_TYPE>
      <LENGTH>12</LENGTH>
      <ABAPTYPE>C</ABAPTYPE>
     </VEPELEMTYPE>
     <VEPELEMTYPE>
      <VEPNAME>ZSD_VEN_GOODSRECEIPT_YM</VEPNAME>
      <VERSION>A</VERSION>
      <TYPENAME>WERKS_D</TYPENAME>
      <KIND>DTEL</KIND>
      <BUILD_IN_TYPE>CHAR</BUILD_IN_TYPE>
      <LENGTH>4</LENGTH>
      <ABAPTYPE>C</ABAPTYPE>
     </VEPELEMTYPE>
    </PVEPELEMTYPE>
    <PVEPTABLETYPE>
     <VEPTABLETYPE>
      <VEPNAME>ZSD_VEN_GOODSRECEIPT_YM</VEPNAME>
      <VERSION>A</VERSION>
      <TYPENAME>ZTT_VEN_RECEIPT_YM</TYPENAME>
      <TYPEREF>ZST_VEN_RECEIPT_YM</TYPEREF>
     </VEPTABLETYPE>
     <VEPTABLETYPE>
      <VEPNAME>ZSD_VEN_GOODSRECEIPT_YM</VEPNAME>
      <VERSION>A</VERSION>
      <TYPENAME>ZttVenReceiptYm</TYPENAME>
      <TYPEREF>ZstVenReceiptYm</TYPEREF>
     </VEPTABLETYPE>
    </PVEPTABLETYPE>
    <PVEPSTRUTYPE>
     <VEPSTRUTYPE>
      <VEPNAME>ZSD_VEN_GOODSRECEIPT_YM</VEPNAME>
      <VERSION>A</VERSION>
      <TYPENAME>ZST_VEN_RECEIPT_YM</TYPENAME>
      <FIELDPOS>1</FIELDPOS>
      <FIELDNAME>MBLNR</FIELDNAME>
      <TYPEREF>MBLNR</TYPEREF>
     </VEPSTRUTYPE>
     <VEPSTRUTYPE>
      <VEPNAME>ZSD_VEN_GOODSRECEIPT_YM</VEPNAME>
      <VERSION>A</VERSION>
      <TYPENAME>ZST_VEN_RECEIPT_YM</TYPENAME>
      <FIELDPOS>2</FIELDPOS>
      <FIELDNAME>MJAHR</FIELDNAME>
      <TYPEREF>MJAHR</TYPEREF>
     </VEPSTRUTYPE>
     <VEPSTRUTYPE>
      <VEPNAME>ZSD_VEN_GOODSRECEIPT_YM</VEPNAME>
      <VERSION>A</VERSION>
      <TYPENAME>ZST_VEN_RECEIPT_YM</TYPENAME>
      <FIELDPOS>3</FIELDPOS>
      <FIELDNAME>BUDAT</FIELDNAME>
      <TYPEREF>BUDAT</TYPEREF>
     </VEPSTRUTYPE>
     <VEPSTRUTYPE>
      <VEPNAME>ZSD_VEN_GOODSRECEIPT_YM</VEPNAME>
      <VERSION>A</VERSION>
      <TYPENAME>ZST_VEN_RECEIPT_YM</TYPENAME>
      <FIELDPOS>4</FIELDPOS>
      <FIELDNAME>BLDAT</FIELDNAME>
      <TYPEREF>BLDAT</TYPEREF>
     </VEPSTRUTYPE>
     <VEPSTRUTYPE>
      <VEPNAME>ZSD_VEN_GOODSRECEIPT_YM</VEPNAME>
      <VERSION>A</VERSION>
      <TYPENAME>ZST_VEN_RECEIPT_YM</TYPENAME>
      <FIELDPOS>5</FIELDPOS>
      <FIELDNAME>BLART</FIELDNAME>
      <TYPEREF>BLART</TYPEREF>
     </VEPSTRUTYPE>
     <VEPSTRUTYPE>
      <VEPNAME>ZSD_VEN_GOODSRECEIPT_YM</VEPNAME>
      <VERSION>A</VERSION>
      <TYPENAME>ZST_VEN_RECEIPT_YM</TYPENAME>
      <FIELDPOS>6</FIELDPOS>
      <FIELDNAME>USNAM</FIELDNAME>
      <TYPEREF>USNAM</TYPEREF>
     </VEPSTRUTYPE>
     <VEPSTRUTYPE>
      <VEPNAME>ZSD_VEN_GOODSRECEIPT_YM</VEPNAME>
      <VERSION>A</VERSION>
      <TYPENAME>ZST_VEN_RECEIPT_YM</TYPENAME>
      <FIELDPOS>7</FIELDPOS>
      <FIELDNAME>ZEILE</FIELDNAME>
      <TYPEREF>MBLPO</TYPEREF>
     </VEPSTRUTYPE>
     <VEPSTRUTYPE>
      <VEPNAME>ZSD_VEN_GOODSRECEIPT_YM</VEPNAME>
      <VERSION>A</VERSION>
      <TYPENAME>ZST_VEN_RECEIPT_YM</TYPENAME>
      <FIELDPOS>8</FIELDPOS>
      <FIELDNAME>EBELN</FIELDNAME>
      <TYPEREF>BSTNR</TYPEREF>
     </VEPSTRUTYPE>
     <VEPSTRUTYPE>
      <VEPNAME>ZSD_VEN_GOODSRECEIPT_YM</VEPNAME>
      <VERSION>A</VERSION>
      <TYPENAME>ZST_VEN_RECEIPT_YM</TYPENAME>
      <FIELDPOS>9</FIELDPOS>
      <FIELDNAME>EBELP</FIELDNAME>
      <TYPEREF>EBELP</TYPEREF>
     </VEPSTRUTYPE>
     <VEPSTRUTYPE>
      <VEPNAME>ZSD_VEN_GOODSRECEIPT_YM</VEPNAME>
      <VERSION>A</VERSION>
      <TYPENAME>ZST_VEN_RECEIPT_YM</TYPENAME>
      <FIELDPOS>10</FIELDPOS>
      <FIELDNAME>BWART</FIELDNAME>
      <TYPEREF>BWART</TYPEREF>
     </VEPSTRUTYPE>
     <VEPSTRUTYPE>
      <VEPNAME>ZSD_VEN_GOODSRECEIPT_YM</VEPNAME>
      <VERSION>A</VERSION>
      <TYPENAME>ZST_VEN_RECEIPT_YM</TYPENAME>
      <FIELDPOS>11</FIELDPOS>
      <FIELDNAME>MENGE</FIELDNAME>
      <TYPEREF>MENGE_D</TYPEREF>
     </VEPSTRUTYPE>
     <VEPSTRUTYPE>
      <VEPNAME>ZSD_VEN_GOODSRECEIPT_YM</VEPNAME>
      <VERSION>A</VERSION>
      <TYPENAME>ZST_VEN_RECEIPT_YM</TYPENAME>
      <FIELDPOS>12</FIELDPOS>
      <FIELDNAME>MEINS</FIELDNAME>
      <TYPEREF>MEINS</TYPEREF>
     </VEPSTRUTYPE>
     <VEPSTRUTYPE>
      <VEPNAME>ZSD_VEN_GOODSRECEIPT_YM</VEPNAME>
      <VERSION>A</VERSION>
      <TYPENAME>ZST_VEN_RECEIPT_YM</TYPENAME>
      <FIELDPOS>13</FIELDPOS>
      <FIELDNAME>WERKS</FIELDNAME>
      <TYPEREF>WERKS_D</TYPEREF>
     </VEPSTRUTYPE>
     <VEPSTRUTYPE>
      <VEPNAME>ZSD_VEN_GOODSRECEIPT_YM</VEPNAME>
      <VERSION>A</VERSION>
      <TYPENAME>ZST_VEN_RECEIPT_YM</TYPENAME>
      <FIELDPOS>14</FIELDPOS>
      <FIELDNAME>LGORT</FIELDNAME>
      <TYPEREF>LGORT_D</TYPEREF>
     </VEPSTRUTYPE>
     <VEPSTRUTYPE>
      <VEPNAME>ZSD_VEN_GOODSRECEIPT_YM</VEPNAME>
      <VERSION>A</VERSION>
      <TYPENAME>ZST_VEN_RECEIPT_YM</TYPENAME>
      <FIELDPOS>15</FIELDPOS>
      <FIELDNAME>MATNR</FIELDNAME>
      <TYPEREF>MATNR</TYPEREF>
     </VEPSTRUTYPE>
     <VEPSTRUTYPE>
      <VEPNAME>ZSD_VEN_GOODSRECEIPT_YM</VEPNAME>
      <VERSION>A</VERSION>
      <TYPENAME>ZST_VEN_RECEIPT_YM</TYPENAME>
      <FIELDPOS>16</FIELDPOS>
      <FIELDNAME>LIFNR</FIELDNAME>
      <TYPEREF>ELIFN</TYPEREF>
     </VEPSTRUTYPE>
     <VEPSTRUTYPE>
      <VEPNAME>ZSD_VEN_GOODSRECEIPT_YM</VEPNAME>
      <VERSION>A</VERSION>
      <TYPENAME>ZstVenReceiptYm</TYPENAME>
      <FIELDPOS>1</FIELDPOS>
      <FIELDNAME>Mblnr</FIELDNAME>
      <TYPEREF>MBLNR</TYPEREF>
     </VEPSTRUTYPE>
     <VEPSTRUTYPE>
      <VEPNAME>ZSD_VEN_GOODSRECEIPT_YM</VEPNAME>
      <VERSION>A</VERSION>
      <TYPENAME>ZstVenReceiptYm</TYPENAME>
      <FIELDPOS>2</FIELDPOS>
      <FIELDNAME>Mjahr</FIELDNAME>
      <TYPEREF>MJAHR</TYPEREF>
     </VEPSTRUTYPE>
     <VEPSTRUTYPE>
      <VEPNAME>ZSD_VEN_GOODSRECEIPT_YM</VEPNAME>
      <VERSION>A</VERSION>
      <TYPENAME>ZstVenReceiptYm</TYPENAME>
      <FIELDPOS>3</FIELDPOS>
      <FIELDNAME>Budat</FIELDNAME>
      <TYPEREF>BUDAT</TYPEREF>
     </VEPSTRUTYPE>
     <VEPSTRUTYPE>
      <VEPNAME>ZSD_VEN_GOODSRECEIPT_YM</VEPNAME>
      <VERSION>A</VERSION>
      <TYPENAME>ZstVenReceiptYm</TYPENAME>
      <FIELDPOS>4</FIELDPOS>
      <FIELDNAME>Bldat</FIELDNAME>
      <TYPEREF>BLDAT</TYPEREF>
     </VEPSTRUTYPE>
     <VEPSTRUTYPE>
      <VEPNAME>ZSD_VEN_GOODSRECEIPT_YM</VEPNAME>
      <VERSION>A</VERSION>
      <TYPENAME>ZstVenReceiptYm</TYPENAME>
      <FIELDPOS>5</FIELDPOS>
      <FIELDNAME>Blart</FIELDNAME>
      <TYPEREF>BLART</TYPEREF>
     </VEPSTRUTYPE>
     <VEPSTRUTYPE>
      <VEPNAME>ZSD_VEN_GOODSRECEIPT_YM</VEPNAME>
      <VERSION>A</VERSION>
      <TYPENAME>ZstVenReceiptYm</TYPENAME>
      <FIELDPOS>6</FIELDPOS>
      <FIELDNAME>Usnam</FIELDNAME>
      <TYPEREF>USNAM</TYPEREF>
     </VEPSTRUTYPE>
     <VEPSTRUTYPE>
      <VEPNAME>ZSD_VEN_GOODSRECEIPT_YM</VEPNAME>
      <VERSION>A</VERSION>
      <TYPENAME>ZstVenReceiptYm</TYPENAME>
      <FIELDPOS>7</FIELDPOS>
      <FIELDNAME>Zeile</FIELDNAME>
      <TYPEREF>MBLPO</TYPEREF>
     </VEPSTRUTYPE>
     <VEPSTRUTYPE>
      <VEPNAME>ZSD_VEN_GOODSRECEIPT_YM</VEPNAME>
      <VERSION>A</VERSION>
      <TYPENAME>ZstVenReceiptYm</TYPENAME>
      <FIELDPOS>8</FIELDPOS>
      <FIELDNAME>Ebeln</FIELDNAME>
      <TYPEREF>BSTNR</TYPEREF>
     </VEPSTRUTYPE>
     <VEPSTRUTYPE>
      <VEPNAME>ZSD_VEN_GOODSRECEIPT_YM</VEPNAME>
      <VERSION>A</VERSION>
      <TYPENAME>ZstVenReceiptYm</TYPENAME>
      <FIELDPOS>9</FIELDPOS>
      <FIELDNAME>Ebelp</FIELDNAME>
      <TYPEREF>EBELP</TYPEREF>
     </VEPSTRUTYPE>
     <VEPSTRUTYPE>
      <VEPNAME>ZSD_VEN_GOODSRECEIPT_YM</VEPNAME>
      <VERSION>A</VERSION>
      <TYPENAME>ZstVenReceiptYm</TYPENAME>
      <FIELDPOS>10</FIELDPOS>
      <FIELDNAME>Bwart</FIELDNAME>
      <TYPEREF>BWART</TYPEREF>
     </VEPSTRUTYPE>
     <VEPSTRUTYPE>
      <VEPNAME>ZSD_VEN_GOODSRECEIPT_YM</VEPNAME>
      <VERSION>A</VERSION>
      <TYPENAME>ZstVenReceiptYm</TYPENAME>
      <FIELDPOS>11</FIELDPOS>
      <FIELDNAME>Menge</FIELDNAME>
      <TYPEREF>MENGE_D</TYPEREF>
     </VEPSTRUTYPE>
     <VEPSTRUTYPE>
      <VEPNAME>ZSD_VEN_GOODSRECEIPT_YM</VEPNAME>
      <VERSION>A</VERSION>
      <TYPENAME>ZstVenReceiptYm</TYPENAME>
      <FIELDPOS>12</FIELDPOS>
      <FIELDNAME>Meins</FIELDNAME>
      <TYPEREF>MEINS</TYPEREF>
     </VEPSTRUTYPE>
     <VEPSTRUTYPE>
      <VEPNAME>ZSD_VEN_GOODSRECEIPT_YM</VEPNAME>
      <VERSION>A</VERSION>
      <TYPENAME>ZstVenReceiptYm</TYPENAME>
      <FIELDPOS>13</FIELDPOS>
      <FIELDNAME>Werks</FIELDNAME>
      <TYPEREF>WERKS_D</TYPEREF>
     </VEPSTRUTYPE>
     <VEPSTRUTYPE>
      <VEPNAME>ZSD_VEN_GOODSRECEIPT_YM</VEPNAME>
      <VERSION>A</VERSION>
      <TYPENAME>ZstVenReceiptYm</TYPENAME>
      <FIELDPOS>14</FIELDPOS>
      <FIELDNAME>Lgort</FIELDNAME>
      <TYPEREF>LGORT_D</TYPEREF>
     </VEPSTRUTYPE>
     <VEPSTRUTYPE>
      <VEPNAME>ZSD_VEN_GOODSRECEIPT_YM</VEPNAME>
      <VERSION>A</VERSION>
      <TYPENAME>ZstVenReceiptYm</TYPENAME>
      <FIELDPOS>15</FIELDPOS>
      <FIELDNAME>Matnr</FIELDNAME>
      <TYPEREF>MATNR</TYPEREF>
     </VEPSTRUTYPE>
     <VEPSTRUTYPE>
      <VEPNAME>ZSD_VEN_GOODSRECEIPT_YM</VEPNAME>
      <VERSION>A</VERSION>
      <TYPENAME>ZstVenReceiptYm</TYPENAME>
      <FIELDPOS>16</FIELDPOS>
      <FIELDNAME>Lifnr</FIELDNAME>
      <TYPEREF>ELIFN</TYPEREF>
     </VEPSTRUTYPE>
    </PVEPSTRUTYPE>
    <PVEPTYPESOAPEXT>
     <VEPTYPESOAPEXT>
      <VEPNAME>ZSD_VEN_GOODSRECEIPT_YM</VEPNAME>
      <VERSION>A</VERSION>
      <TYPENAME>BLART</TYPENAME>
      <NAMESPACE>urn:sap-com:document:sap:rfc:functions</NAMESPACE>
     </VEPTYPESOAPEXT>
     <VEPTYPESOAPEXT>
      <VEPNAME>ZSD_VEN_GOODSRECEIPT_YM</VEPNAME>
      <VERSION>A</VERSION>
      <TYPENAME>BLDAT</TYPENAME>
      <NAMESPACE>urn:sap-com:document:sap:rfc:functions</NAMESPACE>
     </VEPTYPESOAPEXT>
     <VEPTYPESOAPEXT>
      <VEPNAME>ZSD_VEN_GOODSRECEIPT_YM</VEPNAME>
      <VERSION>A</VERSION>
      <TYPENAME>BSTNR</TYPENAME>
      <NAMESPACE>urn:sap-com:document:sap:rfc:functions</NAMESPACE>
     </VEPTYPESOAPEXT>
     <VEPTYPESOAPEXT>
      <VEPNAME>ZSD_VEN_GOODSRECEIPT_YM</VEPNAME>
      <VERSION>A</VERSION>
      <TYPENAME>BUDAT</TYPENAME>
      <NAMESPACE>urn:sap-com:document:sap:rfc:functions</NAMESPACE>
     </VEPTYPESOAPEXT>
     <VEPTYPESOAPEXT>
      <VEPNAME>ZSD_VEN_GOODSRECEIPT_YM</VEPNAME>
      <VERSION>A</VERSION>
      <TYPENAME>BWART</TYPENAME>
      <NAMESPACE>urn:sap-com:document:sap:rfc:functions</NAMESPACE>
     </VEPTYPESOAPEXT>
     <VEPTYPESOAPEXT>
      <VEPNAME>ZSD_VEN_GOODSRECEIPT_YM</VEPNAME>
      <VERSION>A</VERSION>
      <TYPENAME>EBELP</TYPENAME>
      <NAMESPACE>urn:sap-com:document:sap:rfc:functions</NAMESPACE>
     </VEPTYPESOAPEXT>
     <VEPTYPESOAPEXT>
      <VEPNAME>ZSD_VEN_GOODSRECEIPT_YM</VEPNAME>
      <VERSION>A</VERSION>
      <TYPENAME>ELIFN</TYPENAME>
      <NAMESPACE>urn:sap-com:document:sap:rfc:functions</NAMESPACE>
     </VEPTYPESOAPEXT>
     <VEPTYPESOAPEXT>
      <VEPNAME>ZSD_VEN_GOODSRECEIPT_YM</VEPNAME>
      <VERSION>A</VERSION>
      <TYPENAME>LGORT_D</TYPENAME>
      <NAMESPACE>urn:sap-com:document:sap:rfc:functions</NAMESPACE>
     </VEPTYPESOAPEXT>
     <VEPTYPESOAPEXT>
      <VEPNAME>ZSD_VEN_GOODSRECEIPT_YM</VEPNAME>
      <VERSION>A</VERSION>
      <TYPENAME>LIFNR</TYPENAME>
      <NAMESPACE>urn:sap-com:document:sap:rfc:functions</NAMESPACE>
     </VEPTYPESOAPEXT>
     <VEPTYPESOAPEXT>
      <VEPNAME>ZSD_VEN_GOODSRECEIPT_YM</VEPNAME>
      <VERSION>A</VERSION>
      <TYPENAME>MATNR</TYPENAME>
      <NAMESPACE>urn:sap-com:document:sap:rfc:functions</NAMESPACE>
     </VEPTYPESOAPEXT>
     <VEPTYPESOAPEXT>
      <VEPNAME>ZSD_VEN_GOODSRECEIPT_YM</VEPNAME>
      <VERSION>A</VERSION>
      <TYPENAME>MBLNR</TYPENAME>
      <NAMESPACE>urn:sap-com:document:sap:rfc:functions</NAMESPACE>
     </VEPTYPESOAPEXT>
     <VEPTYPESOAPEXT>
      <VEPNAME>ZSD_VEN_GOODSRECEIPT_YM</VEPNAME>
      <VERSION>A</VERSION>
      <TYPENAME>MBLPO</TYPENAME>
      <NAMESPACE>urn:sap-com:document:sap:rfc:functions</NAMESPACE>
     </VEPTYPESOAPEXT>
     <VEPTYPESOAPEXT>
      <VEPNAME>ZSD_VEN_GOODSRECEIPT_YM</VEPNAME>
      <VERSION>A</VERSION>
      <TYPENAME>MEINS</TYPENAME>
      <NAMESPACE>urn:sap-com:document:sap:rfc:functions</NAMESPACE>
     </VEPTYPESOAPEXT>
     <VEPTYPESOAPEXT>
      <VEPNAME>ZSD_VEN_GOODSRECEIPT_YM</VEPNAME>
      <VERSION>A</VERSION>
      <TYPENAME>MENGE_D</TYPENAME>
      <NAMESPACE>urn:sap-com:document:sap:rfc:functions</NAMESPACE>
     </VEPTYPESOAPEXT>
     <VEPTYPESOAPEXT>
      <VEPNAME>ZSD_VEN_GOODSRECEIPT_YM</VEPNAME>
      <VERSION>A</VERSION>
      <TYPENAME>MJAHR</TYPENAME>
      <NAMESPACE>urn:sap-com:document:sap:rfc:functions</NAMESPACE>
     </VEPTYPESOAPEXT>
     <VEPTYPESOAPEXT>
      <VEPNAME>ZSD_VEN_GOODSRECEIPT_YM</VEPNAME>
      <VERSION>A</VERSION>
      <TYPENAME>USNAM</TYPENAME>
      <NAMESPACE>urn:sap-com:document:sap:rfc:functions</NAMESPACE>
     </VEPTYPESOAPEXT>
     <VEPTYPESOAPEXT>
      <VEPNAME>ZSD_VEN_GOODSRECEIPT_YM</VEPNAME>
      <VERSION>A</VERSION>
      <TYPENAME>WERKS_D</TYPENAME>
      <NAMESPACE>urn:sap-com:document:sap:rfc:functions</NAMESPACE>
     </VEPTYPESOAPEXT>
     <VEPTYPESOAPEXT>
      <VEPNAME>ZSD_VEN_GOODSRECEIPT_YM</VEPNAME>
      <VERSION>A</VERSION>
      <TYPENAME>ZST_VEN_RECEIPT_YM</TYPENAME>
      <NAMESPACE>urn:sap-com:document:sap:rfc:functions</NAMESPACE>
     </VEPTYPESOAPEXT>
     <VEPTYPESOAPEXT>
      <VEPNAME>ZSD_VEN_GOODSRECEIPT_YM</VEPNAME>
      <VERSION>A</VERSION>
      <TYPENAME>ZTT_VEN_RECEIPT_YM</TYPENAME>
      <NAMESPACE>urn:sap-com:document:sap:rfc:functions</NAMESPACE>
     </VEPTYPESOAPEXT>
     <VEPTYPESOAPEXT>
      <VEPNAME>ZSD_VEN_GOODSRECEIPT_YM</VEPNAME>
      <VERSION>A</VERSION>
      <TYPENAME>ZstVenReceiptYm</TYPENAME>
      <NAMESPACE>urn:sap-com:document:sap:soap:functions:mc-style</NAMESPACE>
     </VEPTYPESOAPEXT>
     <VEPTYPESOAPEXT>
      <VEPNAME>ZSD_VEN_GOODSRECEIPT_YM</VEPNAME>
      <VERSION>A</VERSION>
      <TYPENAME>ZttVenReceiptYm</TYPENAME>
      <NAMESPACE>urn:sap-com:document:sap:soap:functions:mc-style</NAMESPACE>
     </VEPTYPESOAPEXT>
    </PVEPTYPESOAPEXT>
    <PVEPTABTYPSOAP>
     <VEPTABTYPSOAP>
      <VEPNAME>ZSD_VEN_GOODSRECEIPT_YM</VEPNAME>
      <VERSION>A</VERSION>
      <TYPENAME>ZTT_VEN_RECEIPT_YM</TYPENAME>
      <ITEMLABEL>item</ITEMLABEL>
     </VEPTABTYPSOAP>
    </PVEPTABTYPSOAP>
    <PVEPFUNCSOAPEXT>
     <VEPFUNCSOAPEXT>
      <VEPNAME>ZSD_VEN_GOODSRECEIPT_YM</VEPNAME>
      <VERSION>A</VERSION>
      <FUNCTION>ZFM_VEN_GOODSRECEIPT_YM</FUNCTION>
      <NAMESPACE>urn:sap-com:document:sap:soap:functions:mc-style</NAMESPACE>
      <RESPONSENAME>ZfmVenGoodsreceiptYmResponse</RESPONSENAME>
      <REQUESTNAME>ZfmVenGoodsreceiptYm</REQUESTNAME>
     </VEPFUNCSOAPEXT>
    </PVEPFUNCSOAPEXT>
    <PVEPFIELDREF>
     <VEPFIELDREF>
      <VEPNAME>ZSD_VEN_GOODSRECEIPT_YM</VEPNAME>
      <VERSION>A</VERSION>
      <FUNCTION>ZFM_VEN_GOODSRECEIPT_YM</FUNCTION>
      <VEPPARAM>EV_VEN_GR</VEPPARAM>
      <VEPPARAMTYPE>O</VEPPARAMTYPE>
      <FIELDNAME>EV_VEN_GR</FIELDNAME>
      <SUBSTRUCID>0000000001</SUBSTRUCID>
      <TYPE>T</TYPE>
      <TYPENAME>ZttVenReceiptYm</TYPENAME>
     </VEPFIELDREF>
     <VEPFIELDREF>
      <VEPNAME>ZSD_VEN_GOODSRECEIPT_YM</VEPNAME>
      <VERSION>A</VERSION>
      <FUNCTION>ZFM_VEN_GOODSRECEIPT_YM</FUNCTION>
      <VEPPARAM>EV_VEN_GR</VEPPARAM>
      <VEPPARAMTYPE>O</VEPPARAMTYPE>
      <STRUCID>0000000001</STRUCID>
      <FIELDNAME>EV_VEN_GR</FIELDNAME>
      <SUBSTRUCID>0000000002</SUBSTRUCID>
      <IS_INITIAL>X</IS_INITIAL>
      <TYPE>S</TYPE>
      <TYPENAME>ZstVenReceiptYm</TYPENAME>
     </VEPFIELDREF>
     <VEPFIELDREF>
      <VEPNAME>ZSD_VEN_GOODSRECEIPT_YM</VEPNAME>
      <VERSION>A</VERSION>
      <FUNCTION>ZFM_VEN_GOODSRECEIPT_YM</FUNCTION>
      <VEPPARAM>EV_VEN_GR</VEPPARAM>
      <VEPPARAMTYPE>O</VEPPARAMTYPE>
      <STRUCID>0000000002</STRUCID>
      <FIELDNAME>Blart</FIELDNAME>
      <SUBSTRUCID>0000000007</SUBSTRUCID>
      <IS_INITIAL>X</IS_INITIAL>
      <TYPE>E</TYPE>
      <TYPENAME>BLART</TYPENAME>
     </VEPFIELDREF>
     <VEPFIELDREF>
      <VEPNAME>ZSD_VEN_GOODSRECEIPT_YM</VEPNAME>
      <VERSION>A</VERSION>
      <FUNCTION>ZFM_VEN_GOODSRECEIPT_YM</FUNCTION>
      <VEPPARAM>EV_VEN_GR</VEPPARAM>
      <VEPPARAMTYPE>O</VEPPARAMTYPE>
      <STRUCID>0000000002</STRUCID>
      <FIELDNAME>Bldat</FIELDNAME>
      <SUBSTRUCID>0000000006</SUBSTRUCID>
      <IS_INITIAL>X</IS_INITIAL>
      <TYPE>E</TYPE>
      <TYPENAME>BLDAT</TYPENAME>
     </VEPFIELDREF>
     <VEPFIELDREF>
      <VEPNAME>ZSD_VEN_GOODSRECEIPT_YM</VEPNAME>
      <VERSION>A</VERSION>
      <FUNCTION>ZFM_VEN_GOODSRECEIPT_YM</FUNCTION>
      <VEPPARAM>EV_VEN_GR</VEPPARAM>
      <VEPPARAMTYPE>O</VEPPARAMTYPE>
      <STRUCID>0000000002</STRUCID>
      <FIELDNAME>Budat</FIELDNAME>
      <SUBSTRUCID>0000000005</SUBSTRUCID>
      <IS_INITIAL>X</IS_INITIAL>
      <TYPE>E</TYPE>
      <TYPENAME>BUDAT</TYPENAME>
     </VEPFIELDREF>
     <VEPFIELDREF>
      <VEPNAME>ZSD_VEN_GOODSRECEIPT_YM</VEPNAME>
      <VERSION>A</VERSION>
      <FUNCTION>ZFM_VEN_GOODSRECEIPT_YM</FUNCTION>
      <VEPPARAM>EV_VEN_GR</VEPPARAM>
      <VEPPARAMTYPE>O</VEPPARAMTYPE>
      <STRUCID>0000000002</STRUCID>
      <FIELDNAME>Bwart</FIELDNAME>
      <SUBSTRUCID>0000000012</SUBSTRUCID>
      <IS_INITIAL>X</IS_INITIAL>
      <TYPE>E</TYPE>
      <TYPENAME>BWART</TYPENAME>
     </VEPFIELDREF>
     <VEPFIELDREF>
      <VEPNAME>ZSD_VEN_GOODSRECEIPT_YM</VEPNAME>
      <VERSION>A</VERSION>
      <FUNCTION>ZFM_VEN_GOODSRECEIPT_YM</FUNCTION>
      <VEPPARAM>EV_VEN_GR</VEPPARAM>
      <VEPPARAMTYPE>O</VEPPARAMTYPE>
      <STRUCID>0000000002</STRUCID>
      <FIELDNAME>Ebeln</FIELDNAME>
      <SUBSTRUCID>0000000010</SUBSTRUCID>
      <IS_INITIAL>X</IS_INITIAL>
      <TYPE>E</TYPE>
      <TYPENAME>BSTNR</TYPENAME>
     </VEPFIELDREF>
     <VEPFIELDREF>
      <VEPNAME>ZSD_VEN_GOODSRECEIPT_YM</VEPNAME>
      <VERSION>A</VERSION>
      <FUNCTION>ZFM_VEN_GOODSRECEIPT_YM</FUNCTION>
      <VEPPARAM>EV_VEN_GR</VEPPARAM>
      <VEPPARAMTYPE>O</VEPPARAMTYPE>
      <STRUCID>0000000002</STRUCID>
      <FIELDNAME>Ebelp</FIELDNAME>
      <SUBSTRUCID>0000000011</SUBSTRUCID>
      <IS_INITIAL>X</IS_INITIAL>
      <TYPE>E</TYPE>
      <TYPENAME>EBELP</TYPENAME>
     </VEPFIELDREF>
     <VEPFIELDREF>
      <VEPNAME>ZSD_VEN_GOODSRECEIPT_YM</VEPNAME>
      <VERSION>A</VERSION>
      <FUNCTION>ZFM_VEN_GOODSRECEIPT_YM</FUNCTION>
      <VEPPARAM>EV_VEN_GR</VEPPARAM>
      <VEPPARAMTYPE>O</VEPPARAMTYPE>
      <STRUCID>0000000002</STRUCID>
      <FIELDNAME>Lgort</FIELDNAME>
      <SUBSTRUCID>0000000016</SUBSTRUCID>
      <IS_INITIAL>X</IS_INITIAL>
      <TYPE>E</TYPE>
      <TYPENAME>LGORT_D</TYPENAME>
     </VEPFIELDREF>
     <VEPFIELDREF>
      <VEPNAME>ZSD_VEN_GOODSRECEIPT_YM</VEPNAME>
      <VERSION>A</VERSION>
      <FUNCTION>ZFM_VEN_GOODSRECEIPT_YM</FUNCTION>
      <VEPPARAM>EV_VEN_GR</VEPPARAM>
      <VEPPARAMTYPE>O</VEPPARAMTYPE>
      <STRUCID>0000000002</STRUCID>
      <FIELDNAME>Lifnr</FIELDNAME>
      <SUBSTRUCID>0000000018</SUBSTRUCID>
      <IS_INITIAL>X</IS_INITIAL>
      <TYPE>E</TYPE>
      <TYPENAME>ELIFN</TYPENAME>
     </VEPFIELDREF>
     <VEPFIELDREF>
      <VEPNAME>ZSD_VEN_GOODSRECEIPT_YM</VEPNAME>
      <VERSION>A</VERSION>
      <FUNCTION>ZFM_VEN_GOODSRECEIPT_YM</FUNCTION>
      <VEPPARAM>EV_VEN_GR</VEPPARAM>
      <VEPPARAMTYPE>O</VEPPARAMTYPE>
      <STRUCID>0000000002</STRUCID>
      <FIELDNAME>Matnr</FIELDNAME>
      <SUBSTRUCID>0000000017</SUBSTRUCID>
      <IS_INITIAL>X</IS_INITIAL>
      <TYPE>E</TYPE>
      <TYPENAME>MATNR</TYPENAME>
     </VEPFIELDREF>
     <VEPFIELDREF>
      <VEPNAME>ZSD_VEN_GOODSRECEIPT_YM</VEPNAME>
      <VERSION>A</VERSION>
      <FUNCTION>ZFM_VEN_GOODSRECEIPT_YM</FUNCTION>
      <VEPPARAM>EV_VEN_GR</VEPPARAM>
      <VEPPARAMTYPE>O</VEPPARAMTYPE>
      <STRUCID>0000000002</STRUCID>
      <FIELDNAME>Mblnr</FIELDNAME>
      <SUBSTRUCID>0000000003</SUBSTRUCID>
      <IS_INITIAL>X</IS_INITIAL>
      <TYPE>E</TYPE>
      <TYPENAME>MBLNR</TYPENAME>
     </VEPFIELDREF>
     <VEPFIELDREF>
      <VEPNAME>ZSD_VEN_GOODSRECEIPT_YM</VEPNAME>
      <VERSION>A</VERSION>
      <FUNCTION>ZFM_VEN_GOODSRECEIPT_YM</FUNCTION>
      <VEPPARAM>EV_VEN_GR</VEPPARAM>
      <VEPPARAMTYPE>O</VEPPARAMTYPE>
      <STRUCID>0000000002</STRUCID>
      <FIELDNAME>Meins</FIELDNAME>
      <SUBSTRUCID>0000000014</SUBSTRUCID>
      <IS_INITIAL>X</IS_INITIAL>
      <TYPE>E</TYPE>
      <TYPENAME>MEINS</TYPENAME>
     </VEPFIELDREF>
     <VEPFIELDREF>
      <VEPNAME>ZSD_VEN_GOODSRECEIPT_YM</VEPNAME>
      <VERSION>A</VERSION>
      <FUNCTION>ZFM_VEN_GOODSRECEIPT_YM</FUNCTION>
      <VEPPARAM>EV_VEN_GR</VEPPARAM>
      <VEPPARAMTYPE>O</VEPPARAMTYPE>
      <STRUCID>0000000002</STRUCID>
      <FIELDNAME>Menge</FIELDNAME>
      <SUBSTRUCID>0000000013</SUBSTRUCID>
      <IS_INITIAL>X</IS_INITIAL>
      <TYPE>E</TYPE>
      <TYPENAME>MENGE_D</TYPENAME>
     </VEPFIELDREF>
     <VEPFIELDREF>
      <VEPNAME>ZSD_VEN_GOODSRECEIPT_YM</VEPNAME>
      <VERSION>A</VERSION>
      <FUNCTION>ZFM_VEN_GOODSRECEIPT_YM</FUNCTION>
      <VEPPARAM>EV_VEN_GR</VEPPARAM>
      <VEPPARAMTYPE>O</VEPPARAMTYPE>
      <STRUCID>0000000002</STRUCID>
      <FIELDNAME>Mjahr</FIELDNAME>
      <SUBSTRUCID>0000000004</SUBSTRUCID>
      <IS_INITIAL>X</IS_INITIAL>
      <TYPE>E</TYPE>
      <TYPENAME>MJAHR</TYPENAME>
     </VEPFIELDREF>
     <VEPFIELDREF>
      <VEPNAME>ZSD_VEN_GOODSRECEIPT_YM</VEPNAME>
      <VERSION>A</VERSION>
      <FUNCTION>ZFM_VEN_GOODSRECEIPT_YM</FUNCTION>
      <VEPPARAM>EV_VEN_GR</VEPPARAM>
      <VEPPARAMTYPE>O</VEPPARAMTYPE>
      <STRUCID>0000000002</STRUCID>
      <FIELDNAME>Usnam</FIELDNAME>
      <SUBSTRUCID>0000000008</SUBSTRUCID>
      <IS_INITIAL>X</IS_INITIAL>
      <TYPE>E</TYPE>
      <TYPENAME>USNAM</TYPENAME>
     </VEPFIELDREF>
     <VEPFIELDREF>
      <VEPNAME>ZSD_VEN_GOODSRECEIPT_YM</VEPNAME>
      <VERSION>A</VERSION>
      <FUNCTION>ZFM_VEN_GOODSRECEIPT_YM</FUNCTION>
      <VEPPARAM>EV_VEN_GR</VEPPARAM>
      <VEPPARAMTYPE>O</VEPPARAMTYPE>
      <STRUCID>0000000002</STRUCID>
      <FIELDNAME>Werks</FIELDNAME>
      <SUBSTRUCID>0000000015</SUBSTRUCID>
      <IS_INITIAL>X</IS_INITIAL>
      <TYPE>E</TYPE>
      <TYPENAME>WERKS_D</TYPENAME>
     </VEPFIELDREF>
     <VEPFIELDREF>
      <VEPNAME>ZSD_VEN_GOODSRECEIPT_YM</VEPNAME>
      <VERSION>A</VERSION>
      <FUNCTION>ZFM_VEN_GOODSRECEIPT_YM</FUNCTION>
      <VEPPARAM>EV_VEN_GR</VEPPARAM>
      <VEPPARAMTYPE>O</VEPPARAMTYPE>
      <STRUCID>0000000002</STRUCID>
      <FIELDNAME>Zeile</FIELDNAME>
      <SUBSTRUCID>0000000009</SUBSTRUCID>
      <IS_INITIAL>X</IS_INITIAL>
      <TYPE>E</TYPE>
      <TYPENAME>MBLPO</TYPENAME>
     </VEPFIELDREF>
     <VEPFIELDREF>
      <VEPNAME>ZSD_VEN_GOODSRECEIPT_YM</VEPNAME>
      <VERSION>A</VERSION>
      <FUNCTION>ZFM_VEN_GOODSRECEIPT_YM</FUNCTION>
      <VEPPARAM>IV_DOC</VEPPARAM>
      <VEPPARAMTYPE>I</VEPPARAMTYPE>
      <FIELDNAME>IV_DOC</FIELDNAME>
      <SUBSTRUCID>0000000001</SUBSTRUCID>
      <TYPE>E</TYPE>
      <TYPENAME>LIFNR</TYPENAME>
     </VEPFIELDREF>
    </PVEPFIELDREF>
    <PVEPENDPOINT>
     <VEPENDPOINT>
      <RELID>VI</RELID>
      <VEPNAME>ZSD_VEN_GOODSRECEIPT_YM</VEPNAME>
      <VERSION>A</VERSION>
      <ENDPOINTTYPE>FUNC</ENDPOINTTYPE>
      <DATA_VERSION>1</DATA_VERSION>
      <DEF_START_PT>I</DEF_START_PT>
      <ENDPOINTNAME>ZFM_VEN_GOODSRECEIPT_YM</ENDPOINTNAME>
      <CLUSTR>124</CLUSTR>
     </VEPENDPOINT>
    </PVEPENDPOINT>
    <PVEPVISOAPEXT>
     <VEPVISOAPEXT>
      <VEPNAME>ZSD_VEN_GOODSRECEIPT_YM</VEPNAME>
      <VERSION>A</VERSION>
      <NAMESPACE>urn:sap-com:document:sap:soap:functions:mc-style</NAMESPACE>
      <SOAP_APPL_URI>urn:sap-com:soap:runtime:application:rfc:710</SOAP_APPL_URI>
     </VEPVISOAPEXT>
    </PVEPVISOAPEXT>
    <PWSHEADER>
     <WSHEADER>
      <WSNAME>ZSD_VEN_GOODSRECEIPT_YM</WSNAME>
      <VERSION>A</VERSION>
      <WSNAMEEXT>ZSD_VEN_GOODSRECEIPT_YM</WSNAMEEXT>
      <PREFIX>/sap/bc/srt/rfc/sap/</PREFIX>
      <VINAME>ZSD_VEN_GOODSRECEIPT_YM</VINAME>
     </WSHEADER>
    </PWSHEADER>
    <PWSSOAPPROP>
     <WSSOAPPROP>
      <WSNAME>ZSD_VEN_GOODSRECEIPT_YM</WSNAME>
      <VERSION>A</VERSION>
      <FEATURE>http://www.sap.com/NW05/soap/features/blocking/</FEATURE>
      <SOAPAPP>FUNC</SOAPAPP>
      <FUNCREF>ZfmVenGoodsreceiptYm</FUNCREF>
      <PROPNUM>0001</PROPNUM>
      <PROPNAME>enableBlocking</PROPNAME>
      <VALUE>true</VALUE>
      <PROFILE_URI>PRF_DT_OP_COM_SYNC</PROFILE_URI>
     </WSSOAPPROP>
     <WSSOAPPROP>
      <WSNAME>ZSD_VEN_GOODSRECEIPT_YM</WSNAME>
      <VERSION>A</VERSION>
      <FEATURE>http://www.sap.com/NW05/soap/features/commit/</FEATURE>
      <SOAPAPP>FUNC</SOAPAPP>
      <FUNCREF>ZfmVenGoodsreceiptYm</FUNCREF>
      <PROPNUM>0001</PROPNUM>
      <PROPNAME>enableCommit</PROPNAME>
      <VALUE>false</VALUE>
      <PROFILE_URI>PRF_DT_OP_COM_SYNC</PROFILE_URI>
     </WSSOAPPROP>
     <WSSOAPPROP>
      <WSNAME>ZSD_VEN_GOODSRECEIPT_YM</WSNAME>
      <VERSION>A</VERSION>
      <FEATURE>http://www.sap.com/NW05/soap/features/transaction/</FEATURE>
      <SOAPAPP>FUNC</SOAPAPP>
      <FUNCREF>ZfmVenGoodsreceiptYm</FUNCREF>
      <PROPNUM>0001</PROPNUM>
      <PROPNAME>required</PROPNAME>
      <VALUE>no</VALUE>
      <PROFILE_URI>PRF_DT_OP_COM_SYNC</PROFILE_URI>
     </WSSOAPPROP>
     <WSSOAPPROP>
      <WSNAME>ZSD_VEN_GOODSRECEIPT_YM</WSNAME>
      <VERSION>A</VERSION>
      <FEATURE>http://www.sap.com/NW05/soap/features/wsrm/</FEATURE>
      <SOAPAPP>FUNC</SOAPAPP>
      <FUNCREF>ZfmVenGoodsreceiptYm</FUNCREF>
      <PROPNUM>0001</PROPNUM>
      <PROPNAME>enableWSRM</PROPNAME>
      <VALUE>false</VALUE>
      <PROFILE_URI>PRF_DT_OP_COM_SYNC</PROFILE_URI>
     </WSSOAPPROP>
     <WSSOAPPROP>
      <WSNAME>ZSD_VEN_GOODSRECEIPT_YM</WSNAME>
      <VERSION>A</VERSION>
      <FEATURE>http://www.sap.com/esi/NW05/rif/</FEATURE>
      <SOAPAPP>FUNC</SOAPAPP>
      <FUNCREF>ZfmVenGoodsreceiptYm</FUNCREF>
      <PROPNUM>0001</PROPNUM>
      <PROPNAME>mep</PROPNAME>
      <VALUE>RequestResponse</VALUE>
      <PROFILE_URI>PRF_DT_OP_COM_SYNC</PROFILE_URI>
     </WSSOAPPROP>
     <WSSOAPPROP>
      <WSNAME>ZSD_VEN_GOODSRECEIPT_YM</WSNAME>
      <VERSION>A</VERSION>
      <FEATURE>http://www.sap.com/webas/630/soap/features/authentication/</FEATURE>
      <SOAPAPP>FUNC</SOAPAPP>
      <PROPNUM>0001</PROPNUM>
      <PROPNAME>AuthenticationLevel</PROPNAME>
      <VALUE>Basic</VALUE>
      <PROFILE_URI>PRF_DT_IF_SEC_MEDIUM</PROFILE_URI>
     </WSSOAPPROP>
     <WSSOAPPROP>
      <WSNAME>ZSD_VEN_GOODSRECEIPT_YM</WSNAME>
      <VERSION>A</VERSION>
      <FEATURE>http://www.sap.com/webas/630/soap/features/session/</FEATURE>
      <SOAPAPP>FUNC</SOAPAPP>
      <PROPNUM>0001</PROPNUM>
      <PROPNAME>enableSession</PROPNAME>
      <VALUE>false</VALUE>
      <PROFILE_URI>PRF_DT_IF_COM_STATELESS</PROFILE_URI>
     </WSSOAPPROP>
     <WSSOAPPROP>
      <WSNAME>ZSD_VEN_GOODSRECEIPT_YM</WSNAME>
      <VERSION>A</VERSION>
      <FEATURE>http://www.sap.com/webas/630/soap/features/transportguarantee/</FEATURE>
      <SOAPAPP>FUNC</SOAPAPP>
      <PROPNUM>0001</PROPNUM>
      <PROPNAME>Level</PROPNAME>
      <VALUE>Both</VALUE>
      <PROFILE_URI>PRF_DT_IF_SEC_MEDIUM</PROFILE_URI>
     </WSSOAPPROP>
     <WSSOAPPROP>
      <WSNAME>ZSD_VEN_GOODSRECEIPT_YM</WSNAME>
      <VERSION>A</VERSION>
      <FEATURE>http://www.sap.com/webas/640/soap/features/messageId/</FEATURE>
      <SOAPAPP>FUNC</SOAPAPP>
      <PROPNUM>0001</PROPNUM>
      <PROPNAME>enableMessageId</PROPNAME>
      <VALUE>true</VALUE>
      <PROFILE_URI>PRF_DT_IF_COM_STATELESS</PROFILE_URI>
     </WSSOAPPROP>
    </PWSSOAPPROP>
   </WEBI>
   <SOTR>
    <item>
     <HEADER>
      <CONCEPT>6045BDABF3551FD0B4845CC2633E8000</CONCEPT>
      <CREA_LAN>E</CREA_LAN>
      <TRALA_TYPE>1</TRALA_TYPE>
      <OBJID_VEC>AAg=</OBJID_VEC>
     </HEADER>
     <ENTRIES>
      <SOTR_TEXT>
       <CONCEPT>6045BDABF3551FD0B4845CC2633E8000</CONCEPT>
       <LANGU>E</LANGU>
       <LFD_NUM>0001</LFD_NUM>
       <FLAG_CNTXT>X</FLAG_CNTXT>
       <STATUS>R</STATUS>
       <LENGTH>054</LENGTH>
       <TEXT>SERVICE DEFINITION FOR GOODS RECEIPT</TEXT>
      </SOTR_TEXT>
     </ENTRIES>
    </item>
   </SOTR>
   <SOTR_USE>
    <SOTR_USE>
     <PGMID>R3TR</PGMID>
     <OBJECT>WEBI</OBJECT>
     <OBJ_NAME>ZSD_VEN_GOODSRECEIPT_YM</OBJ_NAME>
     <CONCEPT>6045BDABF3551FD0B4845CC2633E8000</CONCEPT>
     <LFD_NUM>0001</LFD_NUM>
    </SOTR_USE>
   </SOTR_USE>
  </asx:values>
 </asx:abap>
</abapGit>
